Flask_Restless-1.0.0b1.dist-info/DESCRIPTION.rst
Flask_Restless-1.0.0b1.dist-info/METADATA
Flask_Restless-1.0.0b1.dist-info/RECORD
Flask_Restless-1.0.0b1.dist-info/WHEEL
Flask_Restless-1.0.0b1.dist-info/metadata.json
Flask_Restless-1.0.0b1.dist-info/top_level.txt
flask_restless/__init__.py
flask_restless/helpers.py
flask_restless/manager.py
flask_restless/search.py
flask_restless/serialization.py
flask_restless/views/__init__.py
flask_restless/views/base.py
flask_restless/views/function.py
flask_restless/views/helpers.py
flask_restless/views/relationships.py
flask_restless/views/resources.py
tests/__init__.py
tests/helpers.py
tests/test_bulk.py
tests/test_creating.py
tests/test_deleting.py
tests/test_fetching.py
tests/test_filtering.py
tests/test_functions.py
tests/test_jsonpatch.py
tests/test_manager.py
tests/test_metadata.py
tests/test_serialization.py
tests/test_updating.py
tests/test_updatingrelationship.py
tests/test_validation.py
tests/test_jsonapi/__init__.py
tests/test_jsonapi/test_creating_resources.py
tests/test_jsonapi/test_deleting_resources.py
tests/test_jsonapi/test_document_structure.py
tests/test_jsonapi/test_fetching_data.py
tests/test_jsonapi/test_server_responsibilities.py
tests/test_jsonapi/test_updating_relationships.py
tests/test_jsonapi/test_updating_resources.py
