Metadata-Version: 1.1
Name: Flask-Restless
Version: 1.0.0b1
Summary: A Flask extension for easy ReSTful API generation
Home-page: https://github.com/jfinkels/flask-restless
Author: Jeffrey Finkelstein
Author-email: jeffrey.finkelstein@gmail.com
License: GNU AGPLv3+ or BSD
Download-URL: https://pypi.python.org/pypi/Flask-Restless
Keywords: ReST,API,Flask
Platform: any
Classifier: Development Status :: 4 - Beta
Classifier: Environment :: Web Environment
Classifier: Intended Audience :: Developers
Classifier: License :: OSI Approved :: BSD License
Classifier: License :: OSI Approved :: GNU Affero General Public License v3 or later (AGPLv3+)
Classifier: Operating System :: OS Independent
Classifier: Programming Language :: Python
Classifier: Programming Language :: Python :: 2
Classifier: Programming Language :: Python :: 2.6
Classifier: Programming Language :: Python :: 2.7
Classifier: Programming Language :: Python :: 3
Classifier: Programming Language :: Python :: 3.3
Classifier: Programming Language :: Python :: 3.4
Classifier: Topic :: Database :: Front-Ends
Classifier: Topic :: Internet :: WWW/HTTP
Classifier: Topic :: Software Development :: Libraries :: Python Modules
